[
  {
    "id": 1,
    "nombre": "Auriculares Bluetooth Sony",
    "descripcion": "Auriculares inalámbricos con cancelación de ruido y 30 horas de batería.",
    "precio": 59.99,
    "categoria": "Electrónica",
    "imagen_principal": "https://m.media-amazon.com/images/I/61rA+1-Za7L._UF1000,1000_QL80_.jpg",
    "imagenes": [
      {
        "id": 1,
        "url": "https://m.media-amazon.com/images/I/61MgCvWRlpL._AC_SL1024_.jpg",
        "orden": 0
      }
    ],
    "calificacion": 4.5,
    "stock": 100,
    "oferta": false,
    "descuento": 0.0,
    "sku": "AUD-SNY-001",
    "fecha_creacion": "2024-01-01T00:00:00.000Z",
    "activo": true
  },
  {
    "id": 2,
    "nombre": "Cafetera Nespresso",
    "descripcion": "Cafetera compacta de cápsulas con sistema de calentamiento rápido.",
    "precio": 89.99,
    "categoria": "Hogar",
    "imagen_principal": "https://lh3.googleusercontent.com/d/15zXx4izF2d6ROEce_o3ZYX6Nccubp5v9",
    "imagenes": [
      {
        "id": 2,
        "url": "https://lh3.googleusercontent.com/d/15zXx4izF2d6ROEce_o3ZYX6Nccubp5v9",
        "orden": 0
      }
    ],
    "calificacion": 4.0,
    "stock": 90,
    "oferta": true,
    "descuento": 10.0,
    "sku": "CAF-NES-002",
    "fecha_creacion": "2024-01-02T00:00:00.000Z",
    "activo": true
  },
  {
    "id": 3,
    "nombre": "Zapatillas Deportivas Nike",
    "descripcion": "Zapatillas ligeras para running, disponibles en varios colores.",
    "precio": 120.0,
    "categoria": "Ropa y Calzado",
    "imagen_principal": "https://static.nike.com/a/images/t_PDP_936_v1/f_auto,q_auto:eco/34490c6e-0488-4eb3-ad65-28d3d3dbd866/W+NIKE+AIR+MAX+INTRLK+LITE.png",
    "imagenes": [
      {
        "id": 3,
        "url": "https://static.nike.com/a/images/t_PDP_936_v1/f_auto,q_auto:eco/34490c6e-0488-4eb3-ad65-28d3d3dbd866/W+NIKE+AIR+MAX+INTRLK+LITE.png",
        "orden": 0
      }
    ],
    "calificacion": 3.5,
    "stock": 80,
    "oferta": false,
    "descuento": 0.0,
    "sku": "ZAP-NIK-003",
    "fecha_creacion": "2024-01-03T00:00:00.000Z",
    "activo": true
  },
  {
    "id": 4,
    "nombre": "Smartwatch Samsung Galaxy",
    "descripcion": "Reloj inteligente con monitor de frecuencia cardíaca y GPS integrado.",
    "precio": 199.99,
    "categoria": "Electrónica",
    "imagen_principal": "https://m.media-amazon.com/images/I/71SZNup1qrL._UF894,1000_QL80_.jpg",
    "imagenes": [
      {
        "id": 4,
        "url": "https://m.media-amazon.com/images/I/71SZNup1qrL._UF894,1000_QL80_.jpg",
        "orden": 0
      }
    ],
    "calificacion": 5.0,
    "stock": 70,
    "oferta": true,
    "descuento": 20.0,
    "sku": "SWT-SAM-004",
    "fecha_creacion": "2024-01-04T00:00:00.000Z",
    "activo": true
  },
  {
    "id": 5,
    "nombre": "Mochila de Viaje Herschel",
    "descripcion": "Mochila resistente con compartimento para laptop y múltiples bolsillos.",
    "precio": 75.0,
    "categoria": "Accesorios",
    "imagen_principal": "https://m.media-amazon.com/images/I/61UY-lhhlOL._UY1000_.jpg",
    "imagenes": [
      {
        "id": 5,
        "url": "https://m.media-amazon.com/images/I/61UY-lhhlOL._UY1000_.jpg",
        "orden": 0
      }
    ],
    "calificacion": 4.2,
    "stock": 60,
    "oferta": false,
    "descuento": 0.0,
    "sku": "MOC-HER-005",
    "fecha_creacion": "2024-01-05T00:00:00.000Z",
    "activo": true
  },
  {
    "id": 6,
    "nombre": "Juego de Ollas Tefal",
    "descripcion": "Set de ollas antiadherentes para cocina, incluye 5 piezas.",
    "precio": 110.0,
    "categoria": "Hogar",
    "imagen_principal": "https://m.media-amazon.com/images/I/817TFTQAsvL.jpg",
    "imagenes": [
      {
        "id": 6,
        "url": "https://m.media-amazon.com/images/I/817TFTQAsvL.jpg",
        "orden": 0
      }
    ],
    "calificacion": 3.8,
    "stock": 50,
    "oferta": true,
    "descuento": 15.0,
    "sku": "OLL-TEF-006",
    "fecha_creacion": "2024-01-06T00:00:00.000Z",
    "activo": true
  },
  {
    "id": 7,
    "nombre": "Gafas de Sol Ray-Ban",
    "descripcion": "Gafas de sol clásicas con protección UV 400 y montura metálica.",
    "precio": 150.0,
    "categoria": "Accesorios",
    "imagen_principal": "https://cdn.shopify.com/s/files/1/0035/5991/5629/products/8056597918602_2.jpg",
    "imagenes": [
      {
        "id": 7,
        "url": "https://cdn.shopify.com/s/files/1/0035/5991/5629/products/8056597918602_2.jpg",
        "orden": 0
      }
    ],
    "calificacion": 4.7,
    "stock": 40,
    "oferta": false,
    "descuento": 0.0,
    "sku": "GAF-RAY-007",
    "fecha_creacion": "2024-01-07T00:00:00.000Z",
    "activo": true
  },
  {
    "id": 8,
    "nombre": "Tablet Apple iPad",
    "descripcion": "Tablet con pantalla Retina de 10.2 pulgadas y chip A13 Bionic.",
    "precio": 329.0,
    "categoria": "Electrónica",
    "imagen_principal": "https://webonline.macstore.mx/img/sku/ipadapp678_FZ.jpg",
    "imagenes": [
      {
        "id": 8,
        "url": "https://webonline.macstore.mx/img/sku/ipadapp678_FZ.jpg",
        "orden": 0
      }
    ],
    "calificacion": 4.1,
    "stock": 30,
    "oferta": true,
    "descuento": 30.0,
    "sku": "TAB-APP-008",
    "fecha_creacion": "2024-01-08T00:00:00.000Z",
    "activo": true
  },
  {
    "id": 9,
    "nombre": "Monitor LG 27 pulgadas",
    "descripcion": "Monitor IPS con resolución QHD y 75Hz de tasa de refresco.",
    "precio": 220.0,
    "categoria": "Electrónica",
    "imagen_principal": "https://m.media-amazon.com/images/I/81lC7hURadL.UF894,1000_QL80.jpg",
    "imagenes": [
      {
        "id": 9,
        "url": "https://m.media-amazon.com/images/I/81lC7hURadL.UF894,1000_QL80.jpg",
        "orden": 0
      }
    ],
    "calificacion": 3.9,
    "stock": 20,
    "oferta": false,
    "descuento": 0.0,
    "sku": "MON-LG-009",
    "fecha_creacion": "2024-01-09T00:00:00.000Z",
    "activo": true
  },
  {
    "id": 10,
    "nombre": "Smart TV Samsung 55\"",
    "descripcion": "Televisor 4K UHD con HDR y asistentes de voz integrados.",
    "precio": 599.99,
    "categoria": "Electrónica",
    "imagen_principal": "https://i5.walmartimages.com.mx/mg/gm/1p/images/product-images/img_large/00750940183307l.jpg?odnHeight=612&odnWidth=612&odnBg=FFFFFF",
    "imagenes": [
      {
        "id": 10,
        "url": "https://i5.walmartimages.com.mx/mg/gm/1p/images/product-images/img_large/00750940183307l.jpg?odnHeight=612&odnWidth=612&odnBg=FFFFFF",
        "orden": 0
      }
    ],
    "calificacion": 4.6,
    "stock": 10,
    "oferta": true,
    "descuento": 50.0,
    "sku": "TV-SAM-010",
    "fecha_creacion": "2024-01-10T00:00:00.000Z",
    "activo": true
  }
]
